undercurr/__init__.py
undercurr/py.typed
undercurr-0.0.0.dist-info/METADATA
undercurr-0.0.0.dist-info/WHEEL
undercurr-0.0.0.dist-info/RECORD
