Metadata-Version: 2.4
Name: undercurr
Version: 0.0.0
Summary: A task queue and scheduler library providing unified job scheduling and background processing capabilities.
Author-email: Nick Huang <uwu@nafnix.com>
Requires-Python: >=3.11
